mcp_slack/__init__.py
mcp_slack/server.py
mcp_slack-0.0.2.dist-info/METADATA
mcp_slack-0.0.2.dist-info/WHEEL
mcp_slack-0.0.2.dist-info/entry_points.txt
mcp_slack-0.0.2.dist-info/top_level.txt
mcp_slack-0.0.2.dist-info/RECORD
